lab1/collatz.sv
module collatz( input logic         clk,   // Clock
		input logic 	    go,    // Load value from n; start iterating
		input logic  [31:0] n,     // Start value; only read when go = 1
		output logic [31:0] dout,  // Iteration value: true after go = 1
		output logic 	    done); // True when dout reaches 1

   logic busy;
   logic [31:0] temp = 32'b0;
   assign temp = (dout % 2 == 1) ? 3 * dout + 1 : dout / 2;

   /* Replace this comment and the code below with your solution */
   always_ff @(posedge clk) begin
      if (go == 1'b1) begin
         dout <= n;
         busy <= 1'b1;
         done <= 1'b0;
      end else if ((busy == 1'b1) && (done != 1'b1)) begin 
         dout <= temp;
         if (temp == 32'b1) begin
            busy <= 1'b0;
            done <= 1'b1;
         end 
      end
   end

endmodule

lab1/collatz.vcd
$version Generated by VerilatedVcd $end
$timescale 1ps $end
 $scope module TOP $end
  $var wire 1 # clk $end
  $var wire 1 $ go $end
  $var wire 32 % n [31:0] $end
  $var wire 32 & dout [31:0] $end
  $var wire 1 ' done $end
  $scope module collatz $end
   $var wire 1 # clk $end
   $var wire 1 $ go $end
   $var wire 32 % n [31:0] $end
   $var wire 32 & dout [31:0] $end
   $var wire 1 ' done $end
   $var wire 1 ( busy $end
   $var wire 32 ) temp [31:0] $end
  $upscope $end
 $upscope $end
$enddefinitions $end


#0
0#
0$
b00000000000000000000000000000111 %
b00000000000000000000000000000000 &
0'
0(
b00000000000000000000000000000000 )
#10
1#
#20
0#
1$
#30
1#
b00000000000000000000000000000111 &
1(
b00000000000000000000000000010110 )
#40
0#
#50
1#
#60
0#
0$
#70
1#
b00000000000000000000000000010110 &
b00000000000000000000000000001011 )
#80
0#
#90
1#
b00000000000000000000000000001011 &
b00000000000000000000000000100010 )
#100
0#
#110
1#
b00000000000000000000000000100010 &
b00000000000000000000000000010001 )
#120
0#
#130
1#
b00000000000000000000000000010001 &
b00000000000000000000000000110100 )
#140
0#
#150
1#
b00000000000000000000000000110100 &
b00000000000000000000000000011010 )
#160
0#
#170
1#
b00000000000000000000000000011010 &
b00000000000000000000000000001101 )
#180
0#
#190
1#
b00000000000000000000000000001101 &
b00000000000000000000000000101000 )
#200
0#
#210
1#
b00000000000000000000000000101000 &
b00000000000000000000000000010100 )
#220
0#
#230
1#
b00000000000000000000000000010100 &
b00000000000000000000000000001010 )
#240
0#
#250
1#
b00000000000000000000000000001010 &
b00000000000000000000000000000101 )
#260
0#
#270
1#
b00000000000000000000000000000101 &
b00000000000000000000000000010000 )
#280
0#
#290
1#
b00000000000000000000000000010000 &
b00000000000000000000000000001000 )
#300
0#
#310
1#
b00000000000000000000000000001000 &
b00000000000000000000000000000100 )
#320
0#
#330
1#
b00000000000000000000000000000100 &
b00000000000000000000000000000010 )
#340
0#
#350
1#
b00000000000000000000000000000010 &
b00000000000000000000000000000001 )
#360
0#
#370
1#
b00000000000000000000000000000001 &
1'
0(
b00000000000000000000000000000100 )
