lab1/collatz.sv
module collatz( input logic         clk,   // Clock
		input logic 	    go,    // Load value from n; start iterating
		input logic  [31:0] n,     // Start value; only read when go = 1
		output logic [31:0] dout,  // Iteration value: true after go = 1
		output logic 	    done); // True when dout reaches 1

   logic busy;
   logic [31:0] temp = 32'b0;
   assign temp = (dout % 2 == 1) ? 3 * dout + 1 : dout / 2;

   initial begin
      busy = 1'b0;
      dout = 32'd0;
      done = 1'b0;
   end

   always_ff @(posedge clk) begin
      if (go == 1'b1) begin
         dout <= n;
         busy <= 1'b1;
         done <= 1'b0;
      end else if ((busy == 1'b1) && (done != 1'b1)) begin 
         dout <= temp;
         if (temp == 32'b1) begin
            busy <= 1'b0;
            done <= 1'b1;
         end
      end
   end

endmodule

lab1/range.sv
module range
   #(parameter
     RAM_WORDS = 16,            // Number of counts to store in RAM
     RAM_ADDR_BITS = 4)         // Number of RAM address bits
   (input logic         clk,    // Clock
    input logic 	go,     // Read start and start testing
    input logic [31:0] 	start,  // Number to start from or count to read
    output logic 	done,   // True once memory is filled
    output logic [15:0] count); // Iteration count once finished

   logic 		cgo;    // "go" for the Collatz iterator
   logic                cdone;  // "done" from the Collatz iterator
   logic [31:0] 	n;      // number to start the Collatz iterator

// verilator lint_off PINCONNECTEMPTY
   
   // Instantiate the Collatz iterator
   collatz c1(.clk(clk),
	      .go(cgo),
	      .n(n),
	      .done(cdone),
	      .dout());

   logic [RAM_ADDR_BITS - 1:0] 	 num;         // The RAM address to write
   logic 			 running; // True during the iterations

   /* Replace this comment and the code below with your solution,
      which should generate running, done, cgo, n, num, we, and din */
   logic reset_we;
   logic reset_done;
   logic creset;
   logic [RAM_ADDR_BITS:0] wr_count;

   assign we = !reset_we ? cdone : 1'b0;
   assign done = !reset_done ? (wr_count == (RAM_ADDR_BITS + 1)'(RAM_WORDS)) : 1'b0;
   
   always_ff @(posedge clk) begin
      if (go == 1'b1) begin
         running <= 1'b1;
         n <= start;
         num <= '0;
         din <= 16'b1;
         cgo <= 1'b1;
         wr_count <= '0;
         reset_done <= 1'b0;
         if (cgo == 1'b1) begin
            cgo <= 1'b0;
         end
      end else if (done == 1'b1) begin
         reset_done <= 1'b1;
         running <= 1'b0;
      end else if ((running == 1'b1) && (cdone == 1'b0)) begin
         reset_we <= 1'b0;
         cgo <= 1'b0;
         din <= din + 1;
      end else if ((running == 1'b1) && (cdone == 1'b1)) begin
         if (wr_count != (RAM_ADDR_BITS + 1)'(RAM_WORDS - 1)) begin
            cgo <= 1'b1;
         end
         if (cgo == 1'b1) begin
            cgo <= 1'b0;
         end
         if (creset == 1'b0) begin
            num <= num + 1;
            reset_we <= 1'b1;
            creset <= 1'b1;
            n <= n + 1;
            wr_count <= wr_count + 1;
         end else begin
            din <= 16'b1;
            creset <= 1'b0;
         end
      end
   end
   /* Replace this comment and the code above with your solution */
   
   logic 			 we;                    // Write din to addr
   logic [15:0] 		 din;                   // Data to write
   logic [15:0] 		 mem[RAM_WORDS - 1:0];  // The RAM itself
   logic [RAM_ADDR_BITS - 1:0] 	 addr;                  // Address to read/write

   assign addr = we ? num : start[RAM_ADDR_BITS-1:0];
   
   always_ff @(posedge clk) begin
      if (we) mem[addr] <= din;
      count <= mem[addr];      
   end

endmodule

lab1/range.vcd
$version Generated by VerilatedVcd $end
$timescale 1ps $end
 $scope module TOP $end
  $var wire 1 A clk $end
  $var wire 1 B go $end
  $var wire 32 C start [31:0] $end
  $var wire 1 D done $end
  $var wire 16 E count [15:0] $end
  $scope module range $end
   $var wire 32 G RAM_WORDS [31:0] $end
   $var wire 32 H RAM_ADDR_BITS [31:0] $end
   $var wire 1 A clk $end
   $var wire 1 B go $end
   $var wire 32 C start [31:0] $end
   $var wire 1 D done $end
   $var wire 16 E count [15:0] $end
   $var wire 1 # cgo $end
   $var wire 1 $ cdone $end
   $var wire 32 % n [31:0] $end
   $var wire 4 & num [3:0] $end
   $var wire 1 ' running $end
   $var wire 1 ( reset_we $end
   $var wire 1 ) reset_done $end
   $var wire 1 * creset $end
   $var wire 5 + wr_count [4:0] $end
   $var wire 1 , we $end
   $var wire 16 - din [15:0] $end
   $var wire 16 . mem[0] [15:0] $end
   $var wire 16 / mem[1] [15:0] $end
   $var wire 16 0 mem[2] [15:0] $end
   $var wire 16 1 mem[3] [15:0] $end
   $var wire 16 2 mem[4] [15:0] $end
   $var wire 16 3 mem[5] [15:0] $end
   $var wire 16 4 mem[6] [15:0] $end
   $var wire 16 5 mem[7] [15:0] $end
   $var wire 16 6 mem[8] [15:0] $end
   $var wire 16 7 mem[9] [15:0] $end
   $var wire 16 8 mem[10] [15:0] $end
   $var wire 16 9 mem[11] [15:0] $end
   $var wire 16 : mem[12] [15:0] $end
   $var wire 16 ; mem[13] [15:0] $end
   $var wire 16 < mem[14] [15:0] $end
   $var wire 16 = mem[15] [15:0] $end
   $var wire 4 F addr [3:0] $end
   $scope module c1 $end
    $var wire 1 A clk $end
    $var wire 1 # go $end
    $var wire 32 % n [31:0] $end
    $var wire 32 > dout [31:0] $end
    $var wire 1 $ done $end
    $var wire 1 ? busy $end
    $var wire 32 @ temp [31:0] $end
   $upscope $end
  $upscope $end
 $upscope $end
$enddefinitions $end


#0
0#
0$
b00000000000000000000000000000000 %
b0000 &
0'
0(
0)
0*
b00000 +
0,
b0000000000000000 -
b0000000000000000 .
b0000000000000000 /
b0000000000000000 0
b0000000000000000 1
b0000000000000000 2
b0000000000000000 3
b0000000000000000 4
b0000000000000000 5
b0000000000000000 6
b0000000000000000 7
b0000000000000000 8
b0000000000000000 9
b0000000000000000 :
b0000000000000000 ;
b0000000000000000 <
b0000000000000000 =
b00000000000000000000000000000000 >
0?
b00000000000000000000000000000000 @
0A
1B
b00000000000000000000000000000111 C
0D
b0000000000000000 E
b0111 F
b00000000000000000000000000010000 G
b00000000000000000000000000000100 H
#10
1#
b00000000000000000000000000000111 %
1'
b0000000000000001 -
1A
#20
0A
#30
0#
b00000000000000000000000000000111 >
1?
b00000000000000000000000000010110 @
1A
#40
0A
0B
#50
b0000000000000010 -
b00000000000000000000000000010110 >
b00000000000000000000000000001011 @
1A
#60
0A
#70
b0000000000000011 -
b00000000000000000000000000001011 >
b00000000000000000000000000100010 @
1A
#80
0A
#90
b0000000000000100 -
b00000000000000000000000000100010 >
b00000000000000000000000000010001 @
1A
#100
0A
#110
b0000000000000101 -
b00000000000000000000000000010001 >
b00000000000000000000000000110100 @
1A
#120
0A
#130
b0000000000000110 -
b00000000000000000000000000110100 >
b00000000000000000000000000011010 @
1A
#140
0A
#150
b0000000000000111 -
b00000000000000000000000000011010 >
b00000000000000000000000000001101 @
1A
#160
0A
#170
b0000000000001000 -
b00000000000000000000000000001101 >
b00000000000000000000000000101000 @
1A
#180
0A
#190
b0000000000001001 -
b00000000000000000000000000101000 >
b00000000000000000000000000010100 @
1A
#200
0A
#210
b0000000000001010 -
b00000000000000000000000000010100 >
b00000000000000000000000000001010 @
1A
#220
0A
#230
b0000000000001011 -
b00000000000000000000000000001010 >
b00000000000000000000000000000101 @
1A
#240
0A
#250
b0000000000001100 -
b00000000000000000000000000000101 >
b00000000000000000000000000010000 @
1A
#260
0A
#270
b0000000000001101 -
b00000000000000000000000000010000 >
b00000000000000000000000000001000 @
1A
#280
0A
#290
b0000000000001110 -
b00000000000000000000000000001000 >
b00000000000000000000000000000100 @
1A
#300
0A
#310
b0000000000001111 -
b00000000000000000000000000000100 >
b00000000000000000000000000000010 @
1A
#320
0A
#330
b0000000000010000 -
b00000000000000000000000000000010 >
b00000000000000000000000000000001 @
1A
#340
0A
#350
1$
1,
b0000000000010001 -
b00000000000000000000000000000001 >
0?
b00000000000000000000000000000100 @
1A
b0000 F
#360
0A
#370
1#
b00000000000000000000000000001000 %
b0001 &
1(
1*
b00001 +
0,
b0000000000010001 .
1A
b0111 F
#380
0A
#390
0#
0$
0*
b0000000000000001 -
b00000000000000000000000000001000 >
1?
1A
#400
0A
#410
0(
b0000000000000010 -
b00000000000000000000000000000100 >
b00000000000000000000000000000010 @
1A
#420
0A
#430
b0000000000000011 -
b00000000000000000000000000000010 >
b00000000000000000000000000000001 @
1A
#440
0A
#450
1$
1,
b0000000000000100 -
b00000000000000000000000000000001 >
0?
b00000000000000000000000000000100 @
1A
b0001 F
#460
0A
#470
1#
b00000000000000000000000000001001 %
b0010 &
1(
1*
b00010 +
0,
b0000000000000100 /
1A
b0111 F
#480
0A
#490
0#
0$
0*
b0000000000000001 -
b00000000000000000000000000001001 >
1?
b00000000000000000000000000011100 @
1A
#500
0A
#510
0(
b0000000000000010 -
b00000000000000000000000000011100 >
b00000000000000000000000000001110 @
1A
#520
0A
#530
b0000000000000011 -
b00000000000000000000000000001110 >
b00000000000000000000000000000111 @
1A
#540
0A
#550
b0000000000000100 -
b00000000000000000000000000000111 >
b00000000000000000000000000010110 @
1A
#560
0A
#570
b0000000000000101 -
b00000000000000000000000000010110 >
b00000000000000000000000000001011 @
1A
#580
0A
#590
b0000000000000110 -
b00000000000000000000000000001011 >
b00000000000000000000000000100010 @
1A
#600
0A
#610
b0000000000000111 -
b00000000000000000000000000100010 >
b00000000000000000000000000010001 @
1A
#620
0A
#630
b0000000000001000 -
b00000000000000000000000000010001 >
b00000000000000000000000000110100 @
1A
#640
0A
#650
b0000000000001001 -
b00000000000000000000000000110100 >
b00000000000000000000000000011010 @
1A
#660
0A
#670
b0000000000001010 -
b00000000000000000000000000011010 >
b00000000000000000000000000001101 @
1A
#680
0A
#690
b0000000000001011 -
b00000000000000000000000000001101 >
b00000000000000000000000000101000 @
1A
#700
0A
#710
b0000000000001100 -
b00000000000000000000000000101000 >
b00000000000000000000000000010100 @
1A
#720
0A
#730
b0000000000001101 -
b00000000000000000000000000010100 >
b00000000000000000000000000001010 @
1A
#740
0A
#750
b0000000000001110 -
b00000000000000000000000000001010 >
b00000000000000000000000000000101 @
1A
#760
0A
#770
b0000000000001111 -
b00000000000000000000000000000101 >
b00000000000000000000000000010000 @
1A
#780
0A
#790
b0000000000010000 -
b00000000000000000000000000010000 >
b00000000000000000000000000001000 @
1A
#800
0A
#810
b0000000000010001 -
b00000000000000000000000000001000 >
b00000000000000000000000000000100 @
1A
#820
0A
#830
b0000000000010010 -
b00000000000000000000000000000100 >
b00000000000000000000000000000010 @
1A
#840
0A
#850
b0000000000010011 -
b00000000000000000000000000000010 >
b00000000000000000000000000000001 @
1A
#860
0A
#870
1$
1,
b0000000000010100 -
b00000000000000000000000000000001 >
0?
b00000000000000000000000000000100 @
1A
b0010 F
#880
0A
#890
1#
b00000000000000000000000000001010 %
b0011 &
1(
1*
b00011 +
0,
b0000000000010100 0
1A
b0111 F
#900
0A
#910
0#
0$
0*
b0000000000000001 -
b00000000000000000000000000001010 >
1?
b00000000000000000000000000000101 @
1A
#920
0A
#930
0(
b0000000000000010 -
b00000000000000000000000000000101 >
b00000000000000000000000000010000 @
1A
#940
0A
#950
b0000000000000011 -
b00000000000000000000000000010000 >
b00000000000000000000000000001000 @
1A
#960
0A
#970
b0000000000000100 -
b00000000000000000000000000001000 >
b00000000000000000000000000000100 @
1A
#980
0A
#990
b0000000000000101 -
b00000000000000000000000000000100 >
b00000000000000000000000000000010 @
1A
#1000
0A
#1010
b0000000000000110 -
b00000000000000000000000000000010 >
b00000000000000000000000000000001 @
1A
#1020
0A
#1030
1$
1,
b0000000000000111 -
b00000000000000000000000000000001 >
0?
b00000000000000000000000000000100 @
1A
b0011 F
#1040
0A
#1050
1#
b00000000000000000000000000001011 %
b0100 &
1(
1*
b00100 +
0,
b0000000000000111 1
1A
b0111 F
#1060
0A
#1070
0#
0$
0*
b0000000000000001 -
b00000000000000000000000000001011 >
1?
b00000000000000000000000000100010 @
1A
#1080
0A
#1090
0(
b0000000000000010 -
b00000000000000000000000000100010 >
b00000000000000000000000000010001 @
1A
#1100
0A
#1110
b0000000000000011 -
b00000000000000000000000000010001 >
b00000000000000000000000000110100 @
1A
#1120
0A
#1130
b0000000000000100 -
b00000000000000000000000000110100 >
b00000000000000000000000000011010 @
1A
#1140
0A
#1150
b0000000000000101 -
b00000000000000000000000000011010 >
b00000000000000000000000000001101 @
1A
#1160
0A
#1170
b0000000000000110 -
b00000000000000000000000000001101 >
b00000000000000000000000000101000 @
1A
#1180
0A
#1190
b0000000000000111 -
b00000000000000000000000000101000 >
b00000000000000000000000000010100 @
1A
#1200
0A
#1210
b0000000000001000 -
b00000000000000000000000000010100 >
b00000000000000000000000000001010 @
1A
#1220
0A
#1230
b0000000000001001 -
b00000000000000000000000000001010 >
b00000000000000000000000000000101 @
1A
#1240
0A
#1250
b0000000000001010 -
b00000000000000000000000000000101 >
b00000000000000000000000000010000 @
1A
#1260
0A
#1270
b0000000000001011 -
b00000000000000000000000000010000 >
b00000000000000000000000000001000 @
1A
#1280
0A
#1290
b0000000000001100 -
b00000000000000000000000000001000 >
b00000000000000000000000000000100 @
1A
#1300
0A
#1310
b0000000000001101 -
b00000000000000000000000000000100 >
b00000000000000000000000000000010 @
1A
#1320
0A
#1330
b0000000000001110 -
b00000000000000000000000000000010 >
b00000000000000000000000000000001 @
1A
#1340
0A
#1350
1$
1,
b0000000000001111 -
b00000000000000000000000000000001 >
0?
b00000000000000000000000000000100 @
1A
b0100 F
#1360
0A
#1370
1#
b00000000000000000000000000001100 %
b0101 &
1(
1*
b00101 +
0,
b0000000000001111 2
1A
b0111 F
#1380
0A
#1390
0#
0$
0*
b0000000000000001 -
b00000000000000000000000000001100 >
1?
b00000000000000000000000000000110 @
1A
#1400
0A
#1410
0(
b0000000000000010 -
b00000000000000000000000000000110 >
b00000000000000000000000000000011 @
1A
#1420
0A
#1430
b0000000000000011 -
b00000000000000000000000000000011 >
b00000000000000000000000000001010 @
1A
#1440
0A
#1450
b0000000000000100 -
b00000000000000000000000000001010 >
b00000000000000000000000000000101 @
1A
#1460
0A
#1470
b0000000000000101 -
b00000000000000000000000000000101 >
b00000000000000000000000000010000 @
1A
#1480
0A
#1490
b0000000000000110 -
b00000000000000000000000000010000 >
b00000000000000000000000000001000 @
1A
#1500
0A
#1510
b0000000000000111 -
b00000000000000000000000000001000 >
b00000000000000000000000000000100 @
1A
#1520
0A
#1530
b0000000000001000 -
b00000000000000000000000000000100 >
b00000000000000000000000000000010 @
1A
#1540
0A
#1550
b0000000000001001 -
b00000000000000000000000000000010 >
b00000000000000000000000000000001 @
1A
#1560
0A
#1570
1$
1,
b0000000000001010 -
b00000000000000000000000000000001 >
0?
b00000000000000000000000000000100 @
1A
b0101 F
#1580
0A
#1590
1#
b00000000000000000000000000001101 %
b0110 &
1(
1*
b00110 +
0,
b0000000000001010 3
1A
b0111 F
#1600
0A
#1610
0#
0$
0*
b0000000000000001 -
b00000000000000000000000000001101 >
1?
b00000000000000000000000000101000 @
1A
#1620
0A
#1630
0(
b0000000000000010 -
b00000000000000000000000000101000 >
b00000000000000000000000000010100 @
1A
#1640
0A
#1650
b0000000000000011 -
b00000000000000000000000000010100 >
b00000000000000000000000000001010 @
1A
#1660
0A
#1670
b0000000000000100 -
b00000000000000000000000000001010 >
b00000000000000000000000000000101 @
1A
#1680
0A
#1690
b0000000000000101 -
b00000000000000000000000000000101 >
b00000000000000000000000000010000 @
1A
#1700
0A
#1710
b0000000000000110 -
b00000000000000000000000000010000 >
b00000000000000000000000000001000 @
1A
#1720
0A
#1730
b0000000000000111 -
b00000000000000000000000000001000 >
b00000000000000000000000000000100 @
1A
#1740
0A
#1750
b0000000000001000 -
b00000000000000000000000000000100 >
b00000000000000000000000000000010 @
1A
#1760
0A
#1770
b0000000000001001 -
b00000000000000000000000000000010 >
b00000000000000000000000000000001 @
1A
#1780
0A
#1790
1$
1,
b0000000000001010 -
b00000000000000000000000000000001 >
0?
b00000000000000000000000000000100 @
1A
b0110 F
#1800
0A
#1810
1#
b00000000000000000000000000001110 %
b0111 &
1(
1*
b00111 +
0,
b0000000000001010 4
1A
b0111 F
#1820
0A
#1830
0#
0$
0*
b0000000000000001 -
b00000000000000000000000000001110 >
1?
b00000000000000000000000000000111 @
1A
#1840
0A
#1850
0(
b0000000000000010 -
b00000000000000000000000000000111 >
b00000000000000000000000000010110 @
1A
#1860
0A
#1870
b0000000000000011 -
b00000000000000000000000000010110 >
b00000000000000000000000000001011 @
1A
#1880
0A
#1890
b0000000000000100 -
b00000000000000000000000000001011 >
b00000000000000000000000000100010 @
1A
#1900
0A
#1910
b0000000000000101 -
b00000000000000000000000000100010 >
b00000000000000000000000000010001 @
1A
#1920
0A
#1930
b0000000000000110 -
b00000000000000000000000000010001 >
b00000000000000000000000000110100 @
1A
#1940
0A
#1950
b0000000000000111 -
b00000000000000000000000000110100 >
b00000000000000000000000000011010 @
1A
#1960
0A
#1970
b0000000000001000 -
b00000000000000000000000000011010 >
b00000000000000000000000000001101 @
1A
#1980
0A
#1990
b0000000000001001 -
b00000000000000000000000000001101 >
b00000000000000000000000000101000 @
1A
#2000
0A
#2010
b0000000000001010 -
b00000000000000000000000000101000 >
b00000000000000000000000000010100 @
1A
#2020
0A
#2030
b0000000000001011 -
b00000000000000000000000000010100 >
b00000000000000000000000000001010 @
1A
#2040
0A
#2050
b0000000000001100 -
b00000000000000000000000000001010 >
b00000000000000000000000000000101 @
1A
#2060
0A
#2070
b0000000000001101 -
b00000000000000000000000000000101 >
b00000000000000000000000000010000 @
1A
#2080
0A
#2090
b0000000000001110 -
b00000000000000000000000000010000 >
b00000000000000000000000000001000 @
1A
#2100
0A
#2110
b0000000000001111 -
b00000000000000000000000000001000 >
b00000000000000000000000000000100 @
1A
#2120
0A
#2130
b0000000000010000 -
b00000000000000000000000000000100 >
b00000000000000000000000000000010 @
1A
#2140
0A
#2150
b0000000000010001 -
b00000000000000000000000000000010 >
b00000000000000000000000000000001 @
1A
#2160
0A
#2170
1$
1,
b0000000000010010 -
b00000000000000000000000000000001 >
0?
b00000000000000000000000000000100 @
1A
#2180
0A
#2190
1#
b00000000000000000000000000001111 %
b1000 &
1(
1*
b01000 +
0,
b0000000000010010 5
1A
#2200
0A
#2210
0#
0$
0*
b0000000000000001 -
b00000000000000000000000000001111 >
1?
b00000000000000000000000000101110 @
1A
b0000000000010010 E
#2220
0A
#2230
0(
b0000000000000010 -
b00000000000000000000000000101110 >
b00000000000000000000000000010111 @
1A
#2240
0A
#2250
b0000000000000011 -
b00000000000000000000000000010111 >
b00000000000000000000000001000110 @
1A
#2260
0A
#2270
b0000000000000100 -
b00000000000000000000000001000110 >
b00000000000000000000000000100011 @
1A
#2280
0A
#2290
b0000000000000101 -
b00000000000000000000000000100011 >
b00000000000000000000000001101010 @
1A
#2300
0A
#2310
b0000000000000110 -
b00000000000000000000000001101010 >
b00000000000000000000000000110101 @
1A
#2320
0A
#2330
b0000000000000111 -
b00000000000000000000000000110101 >
b00000000000000000000000010100000 @
1A
#2340
0A
#2350
b0000000000001000 -
b00000000000000000000000010100000 >
b00000000000000000000000001010000 @
1A
#2360
0A
#2370
b0000000000001001 -
b00000000000000000000000001010000 >
b00000000000000000000000000101000 @
1A
#2380
0A
#2390
b0000000000001010 -
b00000000000000000000000000101000 >
b00000000000000000000000000010100 @
1A
#2400
0A
#2410
b0000000000001011 -
b00000000000000000000000000010100 >
b00000000000000000000000000001010 @
1A
#2420
0A
#2430
b0000000000001100 -
b00000000000000000000000000001010 >
b00000000000000000000000000000101 @
1A
#2440
0A
#2450
b0000000000001101 -
b00000000000000000000000000000101 >
b00000000000000000000000000010000 @
1A
#2460
0A
#2470
b0000000000001110 -
b00000000000000000000000000010000 >
b00000000000000000000000000001000 @
1A
#2480
0A
#2490
b0000000000001111 -
b00000000000000000000000000001000 >
b00000000000000000000000000000100 @
1A
#2500
0A
#2510
b0000000000010000 -
b00000000000000000000000000000100 >
b00000000000000000000000000000010 @
1A
#2520
0A
#2530
b0000000000010001 -
b00000000000000000000000000000010 >
b00000000000000000000000000000001 @
1A
#2540
0A
#2550
1$
1,
b0000000000010010 -
b00000000000000000000000000000001 >
0?
b00000000000000000000000000000100 @
1A
b1000 F
#2560
0A
#2570
1#
b00000000000000000000000000010000 %
b1001 &
1(
1*
b01001 +
0,
b0000000000010010 6
1A
b0000000000000000 E
b0111 F
#2580
0A
#2590
0#
0$
0*
b0000000000000001 -
b00000000000000000000000000010000 >
1?
b00000000000000000000000000001000 @
1A
b0000000000010010 E
#2600
0A
#2610
0(
b0000000000000010 -
b00000000000000000000000000001000 >
b00000000000000000000000000000100 @
1A
#2620
0A
#2630
b0000000000000011 -
b00000000000000000000000000000100 >
b00000000000000000000000000000010 @
1A
#2640
0A
#2650
b0000000000000100 -
b00000000000000000000000000000010 >
b00000000000000000000000000000001 @
1A
#2660
0A
#2670
1$
1,
b0000000000000101 -
b00000000000000000000000000000001 >
0?
b00000000000000000000000000000100 @
1A
b1001 F
#2680
0A
#2690
1#
b00000000000000000000000000010001 %
b1010 &
1(
1*
b01010 +
0,
b0000000000000101 7
1A
b0000000000000000 E
b0111 F
#2700
0A
#2710
0#
0$
0*
b0000000000000001 -
b00000000000000000000000000010001 >
1?
b00000000000000000000000000110100 @
1A
b0000000000010010 E
#2720
0A
#2730
0(
b0000000000000010 -
b00000000000000000000000000110100 >
b00000000000000000000000000011010 @
1A
#2740
0A
#2750
b0000000000000011 -
b00000000000000000000000000011010 >
b00000000000000000000000000001101 @
1A
#2760
0A
#2770
b0000000000000100 -
b00000000000000000000000000001101 >
b00000000000000000000000000101000 @
1A
#2780
0A
#2790
b0000000000000101 -
b00000000000000000000000000101000 >
b00000000000000000000000000010100 @
1A
#2800
0A
#2810
b0000000000000110 -
b00000000000000000000000000010100 >
b00000000000000000000000000001010 @
1A
#2820
0A
#2830
b0000000000000111 -
b00000000000000000000000000001010 >
b00000000000000000000000000000101 @
1A
#2840
0A
#2850
b0000000000001000 -
b00000000000000000000000000000101 >
b00000000000000000000000000010000 @
1A
#2860
0A
#2870
b0000000000001001 -
b00000000000000000000000000010000 >
b00000000000000000000000000001000 @
1A
#2880
0A
#2890
b0000000000001010 -
b00000000000000000000000000001000 >
b00000000000000000000000000000100 @
1A
#2900
0A
#2910
b0000000000001011 -
b00000000000000000000000000000100 >
b00000000000000000000000000000010 @
1A
#2920
0A
#2930
b0000000000001100 -
b00000000000000000000000000000010 >
b00000000000000000000000000000001 @
1A
#2940
0A
#2950
1$
1,
b0000000000001101 -
b00000000000000000000000000000001 >
0?
b00000000000000000000000000000100 @
1A
b1010 F
#2960
0A
#2970
1#
b00000000000000000000000000010010 %
b1011 &
1(
1*
b01011 +
0,
b0000000000001101 8
1A
b0000000000000000 E
b0111 F
#2980
0A
#2990
0#
0$
0*
b0000000000000001 -
b00000000000000000000000000010010 >
1?
b00000000000000000000000000001001 @
1A
b0000000000010010 E
#3000
0A
#3010
0(
b0000000000000010 -
b00000000000000000000000000001001 >
b00000000000000000000000000011100 @
1A
#3020
0A
#3030
b0000000000000011 -
b00000000000000000000000000011100 >
b00000000000000000000000000001110 @
1A
#3040
0A
#3050
b0000000000000100 -
b00000000000000000000000000001110 >
b00000000000000000000000000000111 @
1A
#3060
0A
#3070
b0000000000000101 -
b00000000000000000000000000000111 >
b00000000000000000000000000010110 @
1A
#3080
0A
#3090
b0000000000000110 -
b00000000000000000000000000010110 >
b00000000000000000000000000001011 @
1A
#3100
0A
#3110
b0000000000000111 -
b00000000000000000000000000001011 >
b00000000000000000000000000100010 @
1A
#3120
0A
#3130
b0000000000001000 -
b00000000000000000000000000100010 >
b00000000000000000000000000010001 @
1A
#3140
0A
#3150
b0000000000001001 -
b00000000000000000000000000010001 >
b00000000000000000000000000110100 @
1A
#3160
0A
#3170
b0000000000001010 -
b00000000000000000000000000110100 >
b00000000000000000000000000011010 @
1A
#3180
0A
#3190
b0000000000001011 -
b00000000000000000000000000011010 >
b00000000000000000000000000001101 @
1A
#3200
0A
#3210
b0000000000001100 -
b00000000000000000000000000001101 >
b00000000000000000000000000101000 @
1A
#3220
0A
#3230
b0000000000001101 -
b00000000000000000000000000101000 >
b00000000000000000000000000010100 @
1A
#3240
0A
#3250
b0000000000001110 -
b00000000000000000000000000010100 >
b00000000000000000000000000001010 @
1A
#3260
0A
#3270
b0000000000001111 -
b00000000000000000000000000001010 >
b00000000000000000000000000000101 @
1A
#3280
0A
#3290
b0000000000010000 -
b00000000000000000000000000000101 >
b00000000000000000000000000010000 @
1A
#3300
0A
#3310
b0000000000010001 -
b00000000000000000000000000010000 >
b00000000000000000000000000001000 @
1A
#3320
0A
#3330
b0000000000010010 -
b00000000000000000000000000001000 >
b00000000000000000000000000000100 @
1A
#3340
0A
#3350
b0000000000010011 -
b00000000000000000000000000000100 >
b00000000000000000000000000000010 @
1A
#3360
0A
#3370
b0000000000010100 -
b00000000000000000000000000000010 >
b00000000000000000000000000000001 @
1A
#3380
0A
#3390
1$
1,
b0000000000010101 -
b00000000000000000000000000000001 >
0?
b00000000000000000000000000000100 @
1A
b1011 F
#3400
0A
#3410
1#
b00000000000000000000000000010011 %
b1100 &
1(
1*
b01100 +
0,
b0000000000010101 9
1A
b0000000000000000 E
b0111 F
#3420
0A
#3430
0#
0$
0*
b0000000000000001 -
b00000000000000000000000000010011 >
1?
b00000000000000000000000000111010 @
1A
b0000000000010010 E
#3440
0A
#3450
0(
b0000000000000010 -
b00000000000000000000000000111010 >
b00000000000000000000000000011101 @
1A
#3460
0A
#3470
b0000000000000011 -
b00000000000000000000000000011101 >
b00000000000000000000000001011000 @
1A
#3480
0A
#3490
b0000000000000100 -
b00000000000000000000000001011000 >
b00000000000000000000000000101100 @
1A
#3500
0A
#3510
b0000000000000101 -
b00000000000000000000000000101100 >
b00000000000000000000000000010110 @
1A
#3520
0A
#3530
b0000000000000110 -
b00000000000000000000000000010110 >
b00000000000000000000000000001011 @
1A
#3540
0A
#3550
b0000000000000111 -
b00000000000000000000000000001011 >
b00000000000000000000000000100010 @
1A
#3560
0A
#3570
b0000000000001000 -
b00000000000000000000000000100010 >
b00000000000000000000000000010001 @
1A
#3580
0A
#3590
b0000000000001001 -
b00000000000000000000000000010001 >
b00000000000000000000000000110100 @
1A
#3600
0A
#3610
b0000000000001010 -
b00000000000000000000000000110100 >
b00000000000000000000000000011010 @
1A
#3620
0A
#3630
b0000000000001011 -
b00000000000000000000000000011010 >
b00000000000000000000000000001101 @
1A
#3640
0A
#3650
b0000000000001100 -
b00000000000000000000000000001101 >
b00000000000000000000000000101000 @
1A
#3660
0A
#3670
b0000000000001101 -
b00000000000000000000000000101000 >
b00000000000000000000000000010100 @
1A
#3680
0A
#3690
b0000000000001110 -
b00000000000000000000000000010100 >
b00000000000000000000000000001010 @
1A
#3700
0A
#3710
b0000000000001111 -
b00000000000000000000000000001010 >
b00000000000000000000000000000101 @
1A
#3720
0A
#3730
b0000000000010000 -
b00000000000000000000000000000101 >
b00000000000000000000000000010000 @
1A
#3740
0A
#3750
b0000000000010001 -
b00000000000000000000000000010000 >
b00000000000000000000000000001000 @
1A
#3760
0A
#3770
b0000000000010010 -
b00000000000000000000000000001000 >
b00000000000000000000000000000100 @
1A
#3780
0A
#3790
b0000000000010011 -
b00000000000000000000000000000100 >
b00000000000000000000000000000010 @
1A
#3800
0A
#3810
b0000000000010100 -
b00000000000000000000000000000010 >
b00000000000000000000000000000001 @
1A
#3820
0A
#3830
1$
1,
b0000000000010101 -
b00000000000000000000000000000001 >
0?
b00000000000000000000000000000100 @
1A
b1100 F
#3840
0A
#3850
1#
b00000000000000000000000000010100 %
b1101 &
1(
1*
b01101 +
0,
b0000000000010101 :
1A
b0000000000000000 E
b0111 F
#3860
0A
#3870
0#
0$
0*
b0000000000000001 -
b00000000000000000000000000010100 >
1?
b00000000000000000000000000001010 @
1A
b0000000000010010 E
#3880
0A
#3890
0(
b0000000000000010 -
b00000000000000000000000000001010 >
b00000000000000000000000000000101 @
1A
#3900
0A
#3910
b0000000000000011 -
b00000000000000000000000000000101 >
b00000000000000000000000000010000 @
1A
#3920
0A
#3930
b0000000000000100 -
b00000000000000000000000000010000 >
b00000000000000000000000000001000 @
1A
#3940
0A
#3950
b0000000000000101 -
b00000000000000000000000000001000 >
b00000000000000000000000000000100 @
1A
#3960
0A
#3970
b0000000000000110 -
b00000000000000000000000000000100 >
b00000000000000000000000000000010 @
1A
#3980
0A
#3990
b0000000000000111 -
b00000000000000000000000000000010 >
b00000000000000000000000000000001 @
1A
#4000
0A
#4010
1$
1,
b0000000000001000 -
b00000000000000000000000000000001 >
0?
b00000000000000000000000000000100 @
1A
b1101 F
#4020
0A
#4030
1#
b00000000000000000000000000010101 %
b1110 &
1(
1*
b01110 +
0,
b0000000000001000 ;
1A
b0000000000000000 E
b0111 F
#4040
0A
#4050
0#
0$
0*
b0000000000000001 -
b00000000000000000000000000010101 >
1?
b00000000000000000000000001000000 @
1A
b0000000000010010 E
#4060
0A
#4070
0(
b0000000000000010 -
b00000000000000000000000001000000 >
b00000000000000000000000000100000 @
1A
#4080
0A
#4090
b0000000000000011 -
b00000000000000000000000000100000 >
b00000000000000000000000000010000 @
1A
#4100
0A
#4110
b0000000000000100 -
b00000000000000000000000000010000 >
b00000000000000000000000000001000 @
1A
#4120
0A
#4130
b0000000000000101 -
b00000000000000000000000000001000 >
b00000000000000000000000000000100 @
1A
#4140
0A
#4150
b0000000000000110 -
b00000000000000000000000000000100 >
b00000000000000000000000000000010 @
1A
#4160
0A
#4170
b0000000000000111 -
b00000000000000000000000000000010 >
b00000000000000000000000000000001 @
1A
#4180
0A
#4190
1$
1,
b0000000000001000 -
b00000000000000000000000000000001 >
0?
b00000000000000000000000000000100 @
1A
b1110 F
#4200
0A
