lab1/collatz.sv
module collatz( input logic         clk,   // Clock
		input logic 	    go,    // Load value from n; start iterating
		input logic  [31:0] n,     // Start value; only read when go = 1
		output logic [31:0] dout,  // Iteration value: true after go = 1
		output logic 	    done); // True when dout reaches 1

   logic busy;
   logic [31:0] next;

   initial begin
      busy = 1'b0;
      dout = 32'd0;
      done = 1'b0;
   end

   always_comb begin
         if (dout[0] == 1'b1) begin
            next = (32'b11 * dout) + 32'b1;
         end else begin 
            next = dout >> 1;
         end
   end

   always_ff @(posedge clk) begin
      if (go) begin
         dout <= n;
         if (n == 32'd1) begin
            busy <= 1'b0;
            done <= 1'b1;
         end else begin
            busy <= 1'b1;
            done <= 1'b0;
         end 

      end else if (busy) begin
         dout <= next;
         if (next == 32'd1) begin
            busy <= 1'b0;
            done <= 1'b1;
         end
      end
   end
endmodule

lab1/range.sv
module range
   #(parameter
     RAM_WORDS = 16,            // Number of counts to store in RAM
     RAM_ADDR_BITS = 4)         // Number of RAM address bits
   (input logic         clk,    // Clock
    input logic 	go,     // Read start and start testing
    input logic [31:0] 	start,  // Number to start from or count to read
    output logic 	done,   // True once memory is filled
    output logic [15:0] count); // Iteration count once finished

   logic 		cgo;    // "go" for the Collatz iterator
   logic                cdone;  // "done" from the Collatz iterator
   logic [31:0] 	n;      // number to start the Collatz iterator

// verilator lint_off PINCONNECTEMPTY
   
   // Instantiate the Collatz iterator
   collatz c1(.clk(clk),
	      .go(cgo),
	      .n(n),
	      .done(cdone),
	      .dout());

   logic [RAM_ADDR_BITS - 1:0] 	 num;         // The RAM address to write
   //logic 			 running; // True during the iterations

   typedef enum {IDLE, RESET_CGO, RUNNING, DONE} State;
   State state;
   logic reset_we;
   logic [RAM_ADDR_BITS:0] write_counter;

   initial begin
      //running = 1'b0;
      cgo = 1'b0;
      n = 32'd0;
      num = '0;

      reset_we = 1'b0;
      write_counter = '0;

      din = 16'd0;
      count = 16'd0;
      state = IDLE;
   end

   assign we = !reset_we ? cdone : 1'b0;
   
   always_ff @(posedge clk) begin
      case (state) 
         IDLE: begin
            if (go) begin
               state <= RESET_CGO;
               //running <= 1'b1; //Set running
               n <= start; //Load start into n
               num <= '0; //Reset num/RAM addr
               din <= 16'b1; //Set din to 1
               cgo <= 1'b1; //Begin cgo pulse
            end else begin
               state <= IDLE;
            end
         end
         RESET_CGO: begin
            din <= 16'b1; //Ensure din at 1
            cgo <= 1'b0; //End cgo pulse
            reset_we <= 1'b0; //Arm we
            state <= RUNNING;
         end
         RUNNING: begin
            din <= din + 1'b1;
            if (cdone) begin
               num <= num + 1'b1; //Increment write address
               reset_we <= 1'b1; //Reset we 
               write_counter <= write_counter + 1'b1;
               if (write_counter < RAM_WORDS - 1) begin
                  n <= n + 1'b1; //Increment n
                  cgo <= 1'b1; //Start collatz again
                  state <= RESET_CGO;
               end else begin
                  state <= DONE;
                  write_counter <= '0; 
                  //running <= 1'b0; //Reset running
                  done <= 1'b1; //Raise done
               end
            end else begin
               state <= RUNNING;
            end
         end 
         DONE: begin
            done <= 1'b0; //End done pulse
            state <= IDLE; //Go back to IDLE
         end
         
         default: state <= IDLE;
      endcase
   end
   
   logic 			 we;                    // Write din to addr
   logic [15:0] 		 din;                   // Data to write
   logic [15:0] 		 mem[RAM_WORDS - 1:0];  // The RAM itself
   logic [RAM_ADDR_BITS - 1:0] 	 addr;                  // Address to read/write

   assign addr = we ? num : start[RAM_ADDR_BITS-1:0];
   
   always_ff @(posedge clk) begin
      if (we) mem[addr] <= din;
      count <= mem[addr];      
   end

endmodule

lab1/range.vcd
$version Generated by VerilatedVcd $end
$timescale 1ps $end
 $scope module TOP $end
  $var wire 1 ? clk $end
  $var wire 1 @ go $end
  $var wire 32 A start [31:0] $end
  $var wire 1 B done $end
  $var wire 16 C count [15:0] $end
  $scope module range $end
   $var wire 32 E RAM_WORDS [31:0] $end
   $var wire 32 F RAM_ADDR_BITS [31:0] $end
   $var wire 1 ? clk $end
   $var wire 1 @ go $end
   $var wire 32 A start [31:0] $end
   $var wire 1 B done $end
   $var wire 16 C count [15:0] $end
   $var wire 1 # cgo $end
   $var wire 1 $ cdone $end
   $var wire 32 % n [31:0] $end
   $var wire 4 & num [3:0] $end
   $var wire 32 ' state [31:0] $end
   $var wire 1 ( reset_we $end
   $var wire 5 ) write_counter [4:0] $end
   $var wire 1 * we $end
   $var wire 16 + din [15:0] $end
   $var wire 16 , mem[0] [15:0] $end
   $var wire 16 - mem[1] [15:0] $end
   $var wire 16 . mem[2] [15:0] $end
   $var wire 16 / mem[3] [15:0] $end
   $var wire 16 0 mem[4] [15:0] $end
   $var wire 16 1 mem[5] [15:0] $end
   $var wire 16 2 mem[6] [15:0] $end
   $var wire 16 3 mem[7] [15:0] $end
   $var wire 16 4 mem[8] [15:0] $end
   $var wire 16 5 mem[9] [15:0] $end
   $var wire 16 6 mem[10] [15:0] $end
   $var wire 16 7 mem[11] [15:0] $end
   $var wire 16 8 mem[12] [15:0] $end
   $var wire 16 9 mem[13] [15:0] $end
   $var wire 16 : mem[14] [15:0] $end
   $var wire 16 ; mem[15] [15:0] $end
   $var wire 4 D addr [3:0] $end
   $scope module c1 $end
    $var wire 1 ? clk $end
    $var wire 1 # go $end
    $var wire 32 % n [31:0] $end
    $var wire 32 < dout [31:0] $end
    $var wire 1 $ done $end
    $var wire 1 = busy $end
    $var wire 32 > next [31:0] $end
   $upscope $end
  $upscope $end
 $upscope $end
$enddefinitions $end


#0
0#
0$
b00000000000000000000000000000000 %
b0000 &
b00000000000000000000000000000000 '
0(
b00000 )
0*
b0000000000000000 +
b0000000000000000 ,
b0000000000000000 -
b0000000000000000 .
b0000000000000000 /
b0000000000000000 0
b0000000000000000 1
b0000000000000000 2
b0000000000000000 3
b0000000000000000 4
b0000000000000000 5
b0000000000000000 6
b0000000000000000 7
b0000000000000000 8
b0000000000000000 9
b0000000000000000 :
b0000000000000000 ;
b00000000000000000000000000000000 <
0=
b00000000000000000000000000000000 >
0?
1@
b00000000000000000000000000000001 A
0B
b0000000000000000 C
b0001 D
b00000000000000000000000000010000 E
b00000000000000000000000000000100 F
#10
1#
b00000000000000000000000000000001 %
b00000000000000000000000000000001 '
b0000000000000001 +
1?
#20
0?
#30
0#
1$
b00000000000000000000000000000010 '
1*
b00000000000000000000000000000001 <
b00000000000000000000000000000100 >
1?
b0000 D
#40
0?
0@
#50
1#
b00000000000000000000000000000010 %
b0001 &
b00000000000000000000000000000001 '
1(
b00001 )
0*
b0000000000000010 +
b0000000000000001 ,
1?
b0001 D
#60
0?
#70
0#
0$
b00000000000000000000000000000010 '
0(
b0000000000000001 +
b00000000000000000000000000000010 <
1=
b00000000000000000000000000000001 >
1?
#80
0?
#90
1$
1*
b0000000000000010 +
b00000000000000000000000000000001 <
0=
b00000000000000000000000000000100 >
1?
#100
0?
#110
1#
b00000000000000000000000000000011 %
b0010 &
b00000000000000000000000000000001 '
1(
b00010 )
0*
b0000000000000011 +
b0000000000000010 -
1?
#120
0?
#130
0#
0$
b00000000000000000000000000000010 '
0(
b0000000000000001 +
b00000000000000000000000000000011 <
1=
b00000000000000000000000000001010 >
1?
b0000000000000010 C
#140
0?
#150
b0000000000000010 +
b00000000000000000000000000001010 <
b00000000000000000000000000000101 >
1?
#160
0?
#170
b0000000000000011 +
b00000000000000000000000000000101 <
b00000000000000000000000000010000 >
1?
#180
0?
#190
b0000000000000100 +
b00000000000000000000000000010000 <
b00000000000000000000000000001000 >
1?
#200
0?
#210
b0000000000000101 +
b00000000000000000000000000001000 <
b00000000000000000000000000000100 >
1?
#220
0?
#230
b0000000000000110 +
b00000000000000000000000000000100 <
b00000000000000000000000000000010 >
1?
#240
0?
#250
b0000000000000111 +
b00000000000000000000000000000010 <
b00000000000000000000000000000001 >
1?
#260
0?
#270
1$
1*
b0000000000001000 +
b00000000000000000000000000000001 <
0=
b00000000000000000000000000000100 >
1?
b0010 D
#280
0?
#290
1#
b00000000000000000000000000000100 %
b0011 &
b00000000000000000000000000000001 '
1(
b00011 )
0*
b0000000000001001 +
b0000000000001000 .
1?
b0000000000000000 C
b0001 D
#300
0?
#310
0#
0$
b00000000000000000000000000000010 '
0(
b0000000000000001 +
b00000000000000000000000000000100 <
1=
b00000000000000000000000000000010 >
1?
b0000000000000010 C
#320
0?
#330
b0000000000000010 +
b00000000000000000000000000000010 <
b00000000000000000000000000000001 >
1?
#340
0?
#350
1$
1*
b0000000000000011 +
b00000000000000000000000000000001 <
0=
b00000000000000000000000000000100 >
1?
b0011 D
#360
0?
#370
1#
b00000000000000000000000000000101 %
b0100 &
b00000000000000000000000000000001 '
1(
b00100 )
0*
b0000000000000100 +
b0000000000000011 /
1?
b0000000000000000 C
b0001 D
#380
0?
#390
0#
0$
b00000000000000000000000000000010 '
0(
b0000000000000001 +
b00000000000000000000000000000101 <
1=
b00000000000000000000000000010000 >
1?
b0000000000000010 C
#400
0?
#410
b0000000000000010 +
b00000000000000000000000000010000 <
b00000000000000000000000000001000 >
1?
#420
0?
#430
b0000000000000011 +
b00000000000000000000000000001000 <
b00000000000000000000000000000100 >
1?
#440
0?
#450
b0000000000000100 +
b00000000000000000000000000000100 <
b00000000000000000000000000000010 >
1?
#460
0?
#470
b0000000000000101 +
b00000000000000000000000000000010 <
b00000000000000000000000000000001 >
1?
#480
0?
#490
1$
1*
b0000000000000110 +
b00000000000000000000000000000001 <
0=
b00000000000000000000000000000100 >
1?
b0100 D
#500
0?
#510
1#
b00000000000000000000000000000110 %
b0101 &
b00000000000000000000000000000001 '
1(
b00101 )
0*
b0000000000000111 +
b0000000000000110 0
1?
b0000000000000000 C
b0001 D
#520
0?
#530
0#
0$
b00000000000000000000000000000010 '
0(
b0000000000000001 +
b00000000000000000000000000000110 <
1=
b00000000000000000000000000000011 >
1?
b0000000000000010 C
#540
0?
#550
b0000000000000010 +
b00000000000000000000000000000011 <
b00000000000000000000000000001010 >
1?
#560
0?
#570
b0000000000000011 +
b00000000000000000000000000001010 <
b00000000000000000000000000000101 >
1?
#580
0?
#590
b0000000000000100 +
b00000000000000000000000000000101 <
b00000000000000000000000000010000 >
1?
#600
0?
#610
b0000000000000101 +
b00000000000000000000000000010000 <
b00000000000000000000000000001000 >
1?
#620
0?
#630
b0000000000000110 +
b00000000000000000000000000001000 <
b00000000000000000000000000000100 >
1?
#640
0?
#650
b0000000000000111 +
b00000000000000000000000000000100 <
b00000000000000000000000000000010 >
1?
#660
0?
#670
b0000000000001000 +
b00000000000000000000000000000010 <
b00000000000000000000000000000001 >
1?
#680
0?
#690
1$
1*
b0000000000001001 +
b00000000000000000000000000000001 <
0=
b00000000000000000000000000000100 >
1?
b0101 D
#700
0?
#710
1#
b00000000000000000000000000000111 %
b0110 &
b00000000000000000000000000000001 '
1(
b00110 )
0*
b0000000000001010 +
b0000000000001001 1
1?
b0000000000000000 C
b0001 D
#720
0?
#730
0#
0$
b00000000000000000000000000000010 '
0(
b0000000000000001 +
b00000000000000000000000000000111 <
1=
b00000000000000000000000000010110 >
1?
b0000000000000010 C
#740
0?
#750
b0000000000000010 +
b00000000000000000000000000010110 <
b00000000000000000000000000001011 >
1?
#760
0?
#770
b0000000000000011 +
b00000000000000000000000000001011 <
b00000000000000000000000000100010 >
1?
#780
0?
#790
b0000000000000100 +
b00000000000000000000000000100010 <
b00000000000000000000000000010001 >
1?
#800
0?
#810
b0000000000000101 +
b00000000000000000000000000010001 <
b00000000000000000000000000110100 >
1?
#820
0?
#830
b0000000000000110 +
b00000000000000000000000000110100 <
b00000000000000000000000000011010 >
1?
#840
0?
#850
b0000000000000111 +
b00000000000000000000000000011010 <
b00000000000000000000000000001101 >
1?
#860
0?
#870
b0000000000001000 +
b00000000000000000000000000001101 <
b00000000000000000000000000101000 >
1?
#880
0?
#890
b0000000000001001 +
b00000000000000000000000000101000 <
b00000000000000000000000000010100 >
1?
#900
0?
#910
b0000000000001010 +
b00000000000000000000000000010100 <
b00000000000000000000000000001010 >
1?
#920
0?
#930
b0000000000001011 +
b00000000000000000000000000001010 <
b00000000000000000000000000000101 >
1?
#940
0?
#950
b0000000000001100 +
b00000000000000000000000000000101 <
b00000000000000000000000000010000 >
1?
#960
0?
#970
b0000000000001101 +
b00000000000000000000000000010000 <
b00000000000000000000000000001000 >
1?
#980
0?
#990
b0000000000001110 +
b00000000000000000000000000001000 <
b00000000000000000000000000000100 >
1?
#1000
0?
#1010
b0000000000001111 +
b00000000000000000000000000000100 <
b00000000000000000000000000000010 >
1?
#1020
0?
#1030
b0000000000010000 +
b00000000000000000000000000000010 <
b00000000000000000000000000000001 >
1?
#1040
0?
#1050
1$
1*
b0000000000010001 +
b00000000000000000000000000000001 <
0=
b00000000000000000000000000000100 >
1?
b0110 D
#1060
0?
#1070
1#
b00000000000000000000000000001000 %
b0111 &
b00000000000000000000000000000001 '
1(
b00111 )
0*
b0000000000010010 +
b0000000000010001 2
1?
b0000000000000000 C
b0001 D
#1080
0?
#1090
0#
0$
b00000000000000000000000000000010 '
0(
b0000000000000001 +
b00000000000000000000000000001000 <
1=
1?
b0000000000000010 C
#1100
0?
#1110
b0000000000000010 +
b00000000000000000000000000000100 <
b00000000000000000000000000000010 >
1?
#1120
0?
#1130
b0000000000000011 +
b00000000000000000000000000000010 <
b00000000000000000000000000000001 >
1?
#1140
0?
#1150
1$
1*
b0000000000000100 +
b00000000000000000000000000000001 <
0=
b00000000000000000000000000000100 >
1?
b0111 D
#1160
0?
#1170
1#
b00000000000000000000000000001001 %
b1000 &
b00000000000000000000000000000001 '
1(
b01000 )
0*
b0000000000000101 +
b0000000000000100 3
1?
b0000000000000000 C
b0001 D
#1180
0?
#1190
0#
0$
b00000000000000000000000000000010 '
0(
b0000000000000001 +
b00000000000000000000000000001001 <
1=
b00000000000000000000000000011100 >
1?
b0000000000000010 C
#1200
0?
#1210
b0000000000000010 +
b00000000000000000000000000011100 <
b00000000000000000000000000001110 >
1?
#1220
0?
#1230
b0000000000000011 +
b00000000000000000000000000001110 <
b00000000000000000000000000000111 >
1?
#1240
0?
#1250
b0000000000000100 +
b00000000000000000000000000000111 <
b00000000000000000000000000010110 >
1?
#1260
0?
#1270
b0000000000000101 +
b00000000000000000000000000010110 <
b00000000000000000000000000001011 >
1?
#1280
0?
#1290
b0000000000000110 +
b00000000000000000000000000001011 <
b00000000000000000000000000100010 >
1?
#1300
0?
#1310
b0000000000000111 +
b00000000000000000000000000100010 <
b00000000000000000000000000010001 >
1?
#1320
0?
#1330
b0000000000001000 +
b00000000000000000000000000010001 <
b00000000000000000000000000110100 >
1?
#1340
0?
#1350
b0000000000001001 +
b00000000000000000000000000110100 <
b00000000000000000000000000011010 >
1?
#1360
0?
#1370
b0000000000001010 +
b00000000000000000000000000011010 <
b00000000000000000000000000001101 >
1?
#1380
0?
#1390
b0000000000001011 +
b00000000000000000000000000001101 <
b00000000000000000000000000101000 >
1?
#1400
0?
#1410
b0000000000001100 +
b00000000000000000000000000101000 <
b00000000000000000000000000010100 >
1?
#1420
0?
#1430
b0000000000001101 +
b00000000000000000000000000010100 <
b00000000000000000000000000001010 >
1?
#1440
0?
#1450
b0000000000001110 +
b00000000000000000000000000001010 <
b00000000000000000000000000000101 >
1?
#1460
0?
#1470
b0000000000001111 +
b00000000000000000000000000000101 <
b00000000000000000000000000010000 >
1?
#1480
0?
#1490
b0000000000010000 +
b00000000000000000000000000010000 <
b00000000000000000000000000001000 >
1?
#1500
0?
#1510
b0000000000010001 +
b00000000000000000000000000001000 <
b00000000000000000000000000000100 >
1?
#1520
0?
#1530
b0000000000010010 +
b00000000000000000000000000000100 <
b00000000000000000000000000000010 >
1?
#1540
0?
#1550
b0000000000010011 +
b00000000000000000000000000000010 <
b00000000000000000000000000000001 >
1?
#1560
0?
#1570
1$
1*
b0000000000010100 +
b00000000000000000000000000000001 <
0=
b00000000000000000000000000000100 >
1?
b1000 D
#1580
0?
#1590
1#
b00000000000000000000000000001010 %
b1001 &
b00000000000000000000000000000001 '
1(
b01001 )
0*
b0000000000010101 +
b0000000000010100 4
1?
b0000000000000000 C
b0001 D
#1600
0?
#1610
0#
0$
b00000000000000000000000000000010 '
0(
b0000000000000001 +
b00000000000000000000000000001010 <
1=
b00000000000000000000000000000101 >
1?
b0000000000000010 C
#1620
0?
#1630
b0000000000000010 +
b00000000000000000000000000000101 <
b00000000000000000000000000010000 >
1?
#1640
0?
#1650
b0000000000000011 +
b00000000000000000000000000010000 <
b00000000000000000000000000001000 >
1?
#1660
0?
#1670
b0000000000000100 +
b00000000000000000000000000001000 <
b00000000000000000000000000000100 >
1?
#1680
0?
#1690
b0000000000000101 +
b00000000000000000000000000000100 <
b00000000000000000000000000000010 >
1?
#1700
0?
#1710
b0000000000000110 +
b00000000000000000000000000000010 <
b00000000000000000000000000000001 >
1?
#1720
0?
#1730
1$
1*
b0000000000000111 +
b00000000000000000000000000000001 <
0=
b00000000000000000000000000000100 >
1?
b1001 D
#1740
0?
#1750
1#
b00000000000000000000000000001011 %
b1010 &
b00000000000000000000000000000001 '
1(
b01010 )
0*
b0000000000001000 +
b0000000000000111 5
1?
b0000000000000000 C
b0001 D
#1760
0?
#1770
0#
0$
b00000000000000000000000000000010 '
0(
b0000000000000001 +
b00000000000000000000000000001011 <
1=
b00000000000000000000000000100010 >
1?
b0000000000000010 C
#1780
0?
#1790
b0000000000000010 +
b00000000000000000000000000100010 <
b00000000000000000000000000010001 >
1?
#1800
0?
#1810
b0000000000000011 +
b00000000000000000000000000010001 <
b00000000000000000000000000110100 >
1?
#1820
0?
#1830
b0000000000000100 +
b00000000000000000000000000110100 <
b00000000000000000000000000011010 >
1?
#1840
0?
#1850
b0000000000000101 +
b00000000000000000000000000011010 <
b00000000000000000000000000001101 >
1?
#1860
0?
#1870
b0000000000000110 +
b00000000000000000000000000001101 <
b00000000000000000000000000101000 >
1?
#1880
0?
#1890
b0000000000000111 +
b00000000000000000000000000101000 <
b00000000000000000000000000010100 >
1?
#1900
0?
#1910
b0000000000001000 +
b00000000000000000000000000010100 <
b00000000000000000000000000001010 >
1?
#1920
0?
#1930
b0000000000001001 +
b00000000000000000000000000001010 <
b00000000000000000000000000000101 >
1?
#1940
0?
#1950
b0000000000001010 +
b00000000000000000000000000000101 <
b00000000000000000000000000010000 >
1?
#1960
0?
#1970
b0000000000001011 +
b00000000000000000000000000010000 <
b00000000000000000000000000001000 >
1?
#1980
0?
#1990
b0000000000001100 +
b00000000000000000000000000001000 <
b00000000000000000000000000000100 >
1?
#2000
0?
#2010
b0000000000001101 +
b00000000000000000000000000000100 <
b00000000000000000000000000000010 >
1?
#2020
0?
#2030
b0000000000001110 +
b00000000000000000000000000000010 <
b00000000000000000000000000000001 >
1?
#2040
0?
#2050
1$
1*
b0000000000001111 +
b00000000000000000000000000000001 <
0=
b00000000000000000000000000000100 >
1?
b1010 D
#2060
0?
#2070
1#
b00000000000000000000000000001100 %
b1011 &
b00000000000000000000000000000001 '
1(
b01011 )
0*
b0000000000010000 +
b0000000000001111 6
1?
b0000000000000000 C
b0001 D
#2080
0?
#2090
0#
0$
b00000000000000000000000000000010 '
0(
b0000000000000001 +
b00000000000000000000000000001100 <
1=
b00000000000000000000000000000110 >
1?
b0000000000000010 C
#2100
0?
#2110
b0000000000000010 +
b00000000000000000000000000000110 <
b00000000000000000000000000000011 >
1?
#2120
0?
#2130
b0000000000000011 +
b00000000000000000000000000000011 <
b00000000000000000000000000001010 >
1?
#2140
0?
#2150
b0000000000000100 +
b00000000000000000000000000001010 <
b00000000000000000000000000000101 >
1?
#2160
0?
#2170
b0000000000000101 +
b00000000000000000000000000000101 <
b00000000000000000000000000010000 >
1?
#2180
0?
#2190
b0000000000000110 +
b00000000000000000000000000010000 <
b00000000000000000000000000001000 >
1?
#2200
0?
#2210
b0000000000000111 +
b00000000000000000000000000001000 <
b00000000000000000000000000000100 >
1?
#2220
0?
#2230
b0000000000001000 +
b00000000000000000000000000000100 <
b00000000000000000000000000000010 >
1?
#2240
0?
#2250
b0000000000001001 +
b00000000000000000000000000000010 <
b00000000000000000000000000000001 >
1?
#2260
0?
#2270
1$
1*
b0000000000001010 +
b00000000000000000000000000000001 <
0=
b00000000000000000000000000000100 >
1?
b1011 D
#2280
0?
#2290
1#
b00000000000000000000000000001101 %
b1100 &
b00000000000000000000000000000001 '
1(
b01100 )
0*
b0000000000001011 +
b0000000000001010 7
1?
b0000000000000000 C
b0001 D
#2300
0?
#2310
0#
0$
b00000000000000000000000000000010 '
0(
b0000000000000001 +
b00000000000000000000000000001101 <
1=
b00000000000000000000000000101000 >
1?
b0000000000000010 C
#2320
0?
#2330
b0000000000000010 +
b00000000000000000000000000101000 <
b00000000000000000000000000010100 >
1?
#2340
0?
#2350
b0000000000000011 +
b00000000000000000000000000010100 <
b00000000000000000000000000001010 >
1?
#2360
0?
#2370
b0000000000000100 +
b00000000000000000000000000001010 <
b00000000000000000000000000000101 >
1?
#2380
0?
#2390
b0000000000000101 +
b00000000000000000000000000000101 <
b00000000000000000000000000010000 >
1?
#2400
0?
#2410
b0000000000000110 +
b00000000000000000000000000010000 <
b00000000000000000000000000001000 >
1?
#2420
0?
#2430
b0000000000000111 +
b00000000000000000000000000001000 <
b00000000000000000000000000000100 >
1?
#2440
0?
#2450
b0000000000001000 +
b00000000000000000000000000000100 <
b00000000000000000000000000000010 >
1?
#2460
0?
#2470
b0000000000001001 +
b00000000000000000000000000000010 <
b00000000000000000000000000000001 >
1?
#2480
0?
#2490
1$
1*
b0000000000001010 +
b00000000000000000000000000000001 <
0=
b00000000000000000000000000000100 >
1?
b1100 D
#2500
0?
#2510
1#
b00000000000000000000000000001110 %
b1101 &
b00000000000000000000000000000001 '
1(
b01101 )
0*
b0000000000001011 +
b0000000000001010 8
1?
b0000000000000000 C
b0001 D
#2520
0?
#2530
0#
0$
b00000000000000000000000000000010 '
0(
b0000000000000001 +
b00000000000000000000000000001110 <
1=
b00000000000000000000000000000111 >
1?
b0000000000000010 C
#2540
0?
#2550
b0000000000000010 +
b00000000000000000000000000000111 <
b00000000000000000000000000010110 >
1?
#2560
0?
#2570
b0000000000000011 +
b00000000000000000000000000010110 <
b00000000000000000000000000001011 >
1?
#2580
0?
#2590
b0000000000000100 +
b00000000000000000000000000001011 <
b00000000000000000000000000100010 >
1?
#2600
0?
#2610
b0000000000000101 +
b00000000000000000000000000100010 <
b00000000000000000000000000010001 >
1?
#2620
0?
#2630
b0000000000000110 +
b00000000000000000000000000010001 <
b00000000000000000000000000110100 >
1?
#2640
0?
#2650
b0000000000000111 +
b00000000000000000000000000110100 <
b00000000000000000000000000011010 >
1?
#2660
0?
#2670
b0000000000001000 +
b00000000000000000000000000011010 <
b00000000000000000000000000001101 >
1?
#2680
0?
#2690
b0000000000001001 +
b00000000000000000000000000001101 <
b00000000000000000000000000101000 >
1?
#2700
0?
#2710
b0000000000001010 +
b00000000000000000000000000101000 <
b00000000000000000000000000010100 >
1?
#2720
0?
#2730
b0000000000001011 +
b00000000000000000000000000010100 <
b00000000000000000000000000001010 >
1?
#2740
0?
#2750
b0000000000001100 +
b00000000000000000000000000001010 <
b00000000000000000000000000000101 >
1?
#2760
0?
#2770
b0000000000001101 +
b00000000000000000000000000000101 <
b00000000000000000000000000010000 >
1?
#2780
0?
#2790
b0000000000001110 +
b00000000000000000000000000010000 <
b00000000000000000000000000001000 >
1?
#2800
0?
#2810
b0000000000001111 +
b00000000000000000000000000001000 <
b00000000000000000000000000000100 >
1?
#2820
0?
#2830
b0000000000010000 +
b00000000000000000000000000000100 <
b00000000000000000000000000000010 >
1?
#2840
0?
#2850
b0000000000010001 +
b00000000000000000000000000000010 <
b00000000000000000000000000000001 >
1?
#2860
0?
#2870
1$
1*
b0000000000010010 +
b00000000000000000000000000000001 <
0=
b00000000000000000000000000000100 >
1?
b1101 D
#2880
0?
#2890
1#
b00000000000000000000000000001111 %
b1110 &
b00000000000000000000000000000001 '
1(
b01110 )
0*
b0000000000010011 +
b0000000000010010 9
1?
b0000000000000000 C
b0001 D
#2900
0?
#2910
0#
0$
b00000000000000000000000000000010 '
0(
b0000000000000001 +
b00000000000000000000000000001111 <
1=
b00000000000000000000000000101110 >
1?
b0000000000000010 C
#2920
0?
#2930
b0000000000000010 +
b00000000000000000000000000101110 <
b00000000000000000000000000010111 >
1?
#2940
0?
#2950
b0000000000000011 +
b00000000000000000000000000010111 <
b00000000000000000000000001000110 >
1?
#2960
0?
#2970
b0000000000000100 +
b00000000000000000000000001000110 <
b00000000000000000000000000100011 >
1?
#2980
0?
#2990
b0000000000000101 +
b00000000000000000000000000100011 <
b00000000000000000000000001101010 >
1?
#3000
0?
#3010
b0000000000000110 +
b00000000000000000000000001101010 <
b00000000000000000000000000110101 >
1?
#3020
0?
#3030
b0000000000000111 +
b00000000000000000000000000110101 <
b00000000000000000000000010100000 >
1?
#3040
0?
#3050
b0000000000001000 +
b00000000000000000000000010100000 <
b00000000000000000000000001010000 >
1?
#3060
0?
#3070
b0000000000001001 +
b00000000000000000000000001010000 <
b00000000000000000000000000101000 >
1?
#3080
0?
#3090
b0000000000001010 +
b00000000000000000000000000101000 <
b00000000000000000000000000010100 >
1?
#3100
0?
#3110
b0000000000001011 +
b00000000000000000000000000010100 <
b00000000000000000000000000001010 >
1?
#3120
0?
#3130
b0000000000001100 +
b00000000000000000000000000001010 <
b00000000000000000000000000000101 >
1?
#3140
0?
#3150
b0000000000001101 +
b00000000000000000000000000000101 <
b00000000000000000000000000010000 >
1?
#3160
0?
#3170
b0000000000001110 +
b00000000000000000000000000010000 <
b00000000000000000000000000001000 >
1?
#3180
0?
#3190
b0000000000001111 +
b00000000000000000000000000001000 <
b00000000000000000000000000000100 >
1?
#3200
0?
#3210
b0000000000010000 +
b00000000000000000000000000000100 <
b00000000000000000000000000000010 >
1?
#3220
0?
#3230
b0000000000010001 +
b00000000000000000000000000000010 <
b00000000000000000000000000000001 >
1?
#3240
0?
#3250
1$
1*
b0000000000010010 +
b00000000000000000000000000000001 <
0=
b00000000000000000000000000000100 >
1?
b1110 D
#3260
0?
#3270
1#
b00000000000000000000000000010000 %
b1111 &
b00000000000000000000000000000001 '
1(
b01111 )
0*
b0000000000010011 +
b0000000000010010 :
1?
b0000000000000000 C
b0001 D
#3280
0?
#3290
0#
0$
b00000000000000000000000000000010 '
0(
b0000000000000001 +
b00000000000000000000000000010000 <
1=
b00000000000000000000000000001000 >
1?
b0000000000000010 C
#3300
0?
#3310
b0000000000000010 +
b00000000000000000000000000001000 <
b00000000000000000000000000000100 >
1?
#3320
0?
#3330
b0000000000000011 +
b00000000000000000000000000000100 <
b00000000000000000000000000000010 >
1?
#3340
0?
#3350
b0000000000000100 +
b00000000000000000000000000000010 <
b00000000000000000000000000000001 >
1?
#3360
0?
#3370
1$
1*
b0000000000000101 +
b00000000000000000000000000000001 <
0=
b00000000000000000000000000000100 >
1?
b1111 D
#3380
0?
#3390
b0000 &
b00000000000000000000000000000011 '
1(
b00000 )
0*
b0000000000000110 +
b0000000000000101 ;
1?
1B
b0000000000000000 C
b0001 D
#3400
0?
b00000000000000000000000000000000 A
b0000 D
#3410
b00000000000000000000000000000000 '
1?
0B
b0000000000000001 C
#3420
0?
b00000000000000000000000000000001 A
b0001 D
#3430
1?
b0000000000000010 C
#3440
0?
b00000000000000000000000000000010 A
b0010 D
#3450
1?
b0000000000001000 C
#3460
0?
b00000000000000000000000000000011 A
b0011 D
#3470
1?
b0000000000000011 C
#3480
0?
b00000000000000000000000000000100 A
b0100 D
#3490
1?
b0000000000000110 C
#3500
0?
b00000000000000000000000000000101 A
b0101 D
#3510
1?
b0000000000001001 C
#3520
0?
b00000000000000000000000000000110 A
b0110 D
#3530
1?
b0000000000010001 C
#3540
0?
b00000000000000000000000000000111 A
b0111 D
#3550
1?
b0000000000000100 C
#3560
0?
b00000000000000000000000000001000 A
b1000 D
#3570
1?
b0000000000010100 C
#3580
0?
b00000000000000000000000000001001 A
b1001 D
#3590
1?
b0000000000000111 C
#3600
0?
b00000000000000000000000000001010 A
b1010 D
#3610
1?
b0000000000001111 C
#3620
0?
b00000000000000000000000000001011 A
b1011 D
#3630
1?
b0000000000001010 C
#3640
0?
b00000000000000000000000000001100 A
b1100 D
#3650
1?
#3660
0?
b00000000000000000000000000001101 A
b1101 D
#3670
1?
b0000000000010010 C
#3680
0?
b00000000000000000000000000001110 A
b1110 D
#3690
1?
#3700
0?
b00000000000000000000000000001111 A
b1111 D
#3710
1?
b0000000000000101 C
